<NinjaTrader>
  <Version>7.0.1000.31</Version>
  <Layout>
    <ChartData xmlns:xsi="http://www.w3.org/2001/XMLSchema-instance" xmlns:xsd="http://www.w3.org/2001/XMLSchema">
      <ActionColorSerialize>n:AntiqueWhite</ActionColorSerialize>
      <AdvancedOptions>false</AdvancedOptions>
      <AlwaysOnTop>false</AlwaysOnTop>
      <AxisColorSerialize>n:Black</AxisColorSerialize>
      <BackColorSerialize>n:ControlDark</BackColorSerialize>
      <BarMarginRight>40</BarMarginRight>
      <BarSpaceIntern>13.377936940485261</BarSpaceIntern>
      <BuyColorSerialize>n:Honeydew</BuyColorSerialize>
      <ChartCursor>CrossHair</ChartCursor>
      <ChartObjectSelection>true</ChartObjectSelection>
      <ChartOpenedInMR>false</ChartOpenedInMR>
      <ChartTraderEnabled>false</ChartTraderEnabled>
      <ChartTraderVisible>false</ChartTraderVisible>
      <ConfirmDirectEntry>false</ConfirmDirectEntry>
      <CrossHairBuyColorSerialize>n:Lime</CrossHairBuyColorSerialize>
      <CrossHairLabelColorSerialize>n:Black</CrossHairLabelColorSerialize>
      <CrossHairSellColorSerialize>n:Red</CrossHairSellColorSerialize>
      <DirectChartEntry>false</DirectChartEntry>
      <EntryPricePenSerializable>
        <Color>n:BurlyWood</Color>
        <DashStyle>Solid</DashStyle>
        <Width>2</Width>
      </EntryPricePenSerializable>
      <EquidistantBars>true</EquidistantBars>
      <FontSerializable>
        <FontFamily>Arial</FontFamily>
        <Size>8</Size>
        <Style>Regular</Style>
      </FontSerializable>
      <GlobalCrossHairScrolling>true</GlobalCrossHairScrolling>
      <HighlightColorSerialize>n:PaleGoldenrod</HighlightColorSerialize>
      <HorizontalGridLines>false</HorizontalGridLines>
      <HorizontalGridLinesPenSerializable>
        <Color>n:ControlLight</Color>
        <DashStyle>Solid</DashStyle>
        <Width>1</Width>
      </HorizontalGridLinesPenSerializable>
      <LabelFormatDay>M/d/yyyy</LabelFormatDay>
      <LabelFormatMinute>HH:mm</LabelFormatMinute>
      <LabelFormatMonth>MM</LabelFormatMonth>
      <LabelFormatSecond>HH:mm:ss</LabelFormatSecond>
      <LabelFormatTick>HH:mm</LabelFormatTick>
      <LabelFormatYear>MM/yyyy</LabelFormatYear>
      <LimitOrderPenSerializable>
        <Color>n:Cyan</Color>
        <DashStyle>Solid</DashStyle>
        <Width>2</Width>
      </LimitOrderPenSerializable>
      <OpenedRealtime>true</OpenedRealtime>
      <OrderEntryMode>0</OrderEntryMode>
      <OrderPercent>25</OrderPercent>
      <OrderPositionAutoScale>true</OrderPositionAutoScale>
      <ParameterType>Ticks</ParameterType>
      <PerformanceUnit>Points</PerformanceUnit>
      <PriceMarkerInactiveSerialize>n:ControlDark</PriceMarkerInactiveSerialize>
      <ProfitTargetPenSerializable>
        <Color>n:Lime</Color>
        <DashStyle>Solid</DashStyle>
        <Width>2</Width>
      </ProfitTargetPenSerializable>
      <RefreshSeconds>0.5</RefreshSeconds>
      <ScaleQuantity>0</ScaleQuantity>
      <SellColorSerialize>n:LavenderBlush</SellColorSerialize>
      <ShowRealizedProfitLoss>false</ShowRealizedProfitLoss>
      <ShowScrollBar>true</ShowScrollBar>
      <SimulatedOrderVolumeTrigger>0</SimulatedOrderVolumeTrigger>
      <SimulationBackColorSerialize>n:SlateGray</SimulationBackColorSerialize>
      <SnapModeBar>false</SnapModeBar>
      <SnapModePrice>false</SnapModePrice>
      <SplitterPenSerializable>
        <Color>n:Black</Color>
        <DashStyle>Solid</DashStyle>
        <Width>1</Width>
      </SplitterPenSerializable>
      <StayInDrawMode>false</StayInDrawMode>
      <StopLimitOffset>Off</StopLimitOffset>
      <StopLimitOrderPenSerializable>
        <Color>n:Violet</Color>
        <DashStyle>Solid</DashStyle>
        <Width>2</Width>
      </StopLimitOrderPenSerializable>
      <StopLossPenSerializable>
        <Color>n:Red</Color>
        <DashStyle>Solid</DashStyle>
        <Width>2</Width>
      </StopLossPenSerializable>
      <StopMarketDefault>false</StopMarketDefault>
      <StopMarketOrderPenSerializable>
        <Color>n:Pink</Color>
        <DashStyle>Solid</DashStyle>
        <Width>2</Width>
      </StopMarketOrderPenSerializable>
      <AtmStrategySelectionMode>SelectActiveAtmStrategyOnOrderSubmission</AtmStrategySelectionMode>
      <ToolBarEnabled>true</ToolBarEnabled>
      <UseStopMarket>false</UseStopMarket>
      <VerticalGridLines>false</VerticalGridLines>
      <VerticalGridLinesPenSerializable>
        <Color>n:ControlLight</Color>
        <DashStyle>Solid</DashStyle>
        <Width>1</Width>
      </VerticalGridLinesPenSerializable>
    </ChartData>
  </Layout>
  <Indicators>
    <Indicator0>
      <ClassName>NinjaTrader.Indicator.ApexDiagnosticToolbarShortcut</ClassName>
      <Input>
        <PriceType>Close</PriceType>
      </Input>
      <BarsSeriesIdx>0</BarsSeriesIdx>
      <Indicator>
        <ApexDiagnosticToolbarShortcut xmlns:xsi="http://www.w3.org/2001/XMLSchema-instance" xmlns:xsd="http://www.w3.org/2001/XMLSchema">
          <AllowRemovalOfDrawObjects>false</AllowRemovalOfDrawObjects>
          <AutoScale>true</AutoScale>
          <BarsPeriods>
            <Period>
              <BasePeriodType>Tick</BasePeriodType>
              <BasePeriodValue>100</BasePeriodValue>
              <Id>Custom8</Id>
              <MarketDataType>Last</MarketDataType>
              <PointAndFigurePriceType>Close</PointAndFigurePriceType>
              <ReversalType>Tick</ReversalType>
              <Value>10</Value>
              <Value2>50</Value2>
            </Period>
          </BarsPeriods>
          <CalculateOnBarClose>true</CalculateOnBarClose>
          <DisableScaleBuffer>false</DisableScaleBuffer>
          <Displacement>0</Displacement>
          <DisplayInDataBox>false</DisplayInDataBox>
          <DrawOnPricePanel>true</DrawOnPricePanel>
          <Enabled>true</Enabled>
          <ForceMaximumBarsLookBack256>false</ForceMaximumBarsLookBack256>
          <HorizontalGridLines>true</HorizontalGridLines>
          <InstrumentsSerializable>YM 06-16 Globex</InstrumentsSerializable>
          <Lines />
          <LinesConfigurable>true</LinesConfigurable>
          <MaximumBarsLookBack>TwoHundredFiftySix</MaximumBarsLookBack>
          <Name>A.P.E.X. Diagnostic Toolbar Shortcut</Name>
          <Overlay>true</Overlay>
          <PaintPriceMarkers>true</PaintPriceMarkers>
          <Panel>-2</Panel>
          <PanelUI>-1</PanelUI>
          <Plots>
            <Plot>
              <Max>1.7976931348623157E+308</Max>
              <Min>-1.7976931348623157E+308</Min>
              <Name>Dummy</Name>
              <PenSerializable>
                <Color>n:Orange</Color>
                <DashStyle>Solid</DashStyle>
                <Width>1</Width>
              </PenSerializable>
              <PlotStyle>Line</PlotStyle>
            </Plot>
          </Plots>
          <PlotsConfigurable>false</PlotsConfigurable>
          <ScaleJustification>Right</ScaleJustification>
          <SelectedSeries>0</SelectedSeries>
          <SessionBreakLines>true</SessionBreakLines>
          <VerticalGridLines>true</VerticalGridLines>
          <ZOrder>30014</ZOrder>
          <ShowLines>true</ShowLines>
          <ShowFibs>true</ShowFibs>
          <ShowChannels>true</ShowChannels>
          <ShowShapes>true</ShowShapes>
          <ShowMarkers>true</ShowMarkers>
        </ApexDiagnosticToolbarShortcut>
      </Indicator>
    </Indicator0>
    <Indicator1>
      <ClassName>NinjaTrader.Indicator.SolidDeviation_03</ClassName>
      <Input>
        <PriceType>Close</PriceType>
      </Input>
      <BarsSeriesIdx>0</BarsSeriesIdx>
      <Indicator>
        <SolidDeviation_03 xmlns:xsi="http://www.w3.org/2001/XMLSchema-instance" xmlns:xsd="http://www.w3.org/2001/XMLSchema">
          <AllowRemovalOfDrawObjects>false</AllowRemovalOfDrawObjects>
          <AutoScale>true</AutoScale>
          <BarsPeriods>
            <Period>
              <BasePeriodType>Tick</BasePeriodType>
              <BasePeriodValue>100</BasePeriodValue>
              <Id>Custom8</Id>
              <MarketDataType>Last</MarketDataType>
              <PointAndFigurePriceType>Close</PointAndFigurePriceType>
              <ReversalType>Tick</ReversalType>
              <Value>10</Value>
              <Value2>50</Value2>
            </Period>
            <Period>
              <BasePeriodType>Minute</BasePeriodType>
              <BasePeriodValue>1</BasePeriodValue>
              <Id>Minute</Id>
              <MarketDataType>Last</MarketDataType>
              <PointAndFigurePriceType>Close</PointAndFigurePriceType>
              <ReversalType>Tick</ReversalType>
              <Value>1</Value>
              <Value2>1</Value2>
            </Period>
          </BarsPeriods>
          <CalculateOnBarClose>false</CalculateOnBarClose>
          <DisableScaleBuffer>false</DisableScaleBuffer>
          <Displacement>0</Displacement>
          <DisplayInDataBox>true</DisplayInDataBox>
          <DrawOnPricePanel>true</DrawOnPricePanel>
          <Enabled>true</Enabled>
          <ForceMaximumBarsLookBack256>false</ForceMaximumBarsLookBack256>
          <HorizontalGridLines>true</HorizontalGridLines>
          <InstrumentsSerializable>YM 06-16 Globex|YM 06-16 Globex</InstrumentsSerializable>
          <Lines>
            <Line>
              <Name>Zero</Name>
              <PenSerializable>
                <Color>n:Black</Color>
                <DashStyle>Solid</DashStyle>
                <Width>3</Width>
              </PenSerializable>
              <Value>0</Value>
            </Line>
            <Line>
              <Name>+0.7 DD</Name>
              <PenSerializable>
                <Color>n:Black</Color>
                <DashStyle>Dash</DashStyle>
                <Width>1</Width>
              </PenSerializable>
              <Value>0.7</Value>
            </Line>
            <Line>
              <Name>+1 DD</Name>
              <PenSerializable>
                <Color>n:Black</Color>
                <DashStyle>Solid</DashStyle>
                <Width>3</Width>
              </PenSerializable>
              <Value>1</Value>
            </Line>
            <Line>
              <Name>+1.5 DD</Name>
              <PenSerializable>
                <Color>n:Black</Color>
                <DashStyle>Dash</DashStyle>
                <Width>1</Width>
              </PenSerializable>
              <Value>1.5</Value>
            </Line>
            <Line>
              <Name>+2 DD</Name>
              <PenSerializable>
                <Color>n:Black</Color>
                <DashStyle>Solid</DashStyle>
                <Width>1</Width>
              </PenSerializable>
              <Value>2</Value>
            </Line>
            <Line>
              <Name>+3 DD</Name>
              <PenSerializable>
                <Color>n:Black</Color>
                <DashStyle>Solid</DashStyle>
                <Width>3</Width>
              </PenSerializable>
              <Value>3</Value>
            </Line>
          </Lines>
          <LinesConfigurable>true</LinesConfigurable>
          <MaximumBarsLookBack>Infinite</MaximumBarsLookBack>
          <Name />
          <Overlay>false</Overlay>
          <PaintPriceMarkers>true</PaintPriceMarkers>
          <Panel>1</Panel>
          <PanelUI>2</PanelUI>
          <Plots>
            <Plot>
              <Max>1.7976931348623157E+308</Max>
              <Min>-1.7976931348623157E+308</Min>
              <Name>Days range</Name>
              <PenSerializable>
                <Color>n:Blue</Color>
                <DashStyle>Dash</DashStyle>
                <Width>2</Width>
              </PenSerializable>
              <PlotStyle>Line</PlotStyle>
            </Plot>
            <Plot>
              <Max>1.7976931348623157E+308</Max>
              <Min>-1.7976931348623157E+308</Min>
              <Name>From settlement</Name>
              <PenSerializable>
                <Color>n:Transparent</Color>
                <DashStyle>Dash</DashStyle>
                <Width>1</Width>
              </PenSerializable>
              <PlotStyle>Line</PlotStyle>
            </Plot>
            <Plot>
              <Max>1.7976931348623157E+308</Max>
              <Min>-1.7976931348623157E+308</Min>
              <Name>From low</Name>
              <PenSerializable>
                <Color>x:b2d2691e</Color>
                <DashStyle>Solid</DashStyle>
                <Width>13</Width>
              </PenSerializable>
              <PlotStyle>Bar</PlotStyle>
            </Plot>
            <Plot>
              <Max>1.7976931348623157E+308</Max>
              <Min>-1.7976931348623157E+308</Min>
              <Name>From high</Name>
              <PenSerializable>
                <Color>x:b24682b4</Color>
                <DashStyle>Solid</DashStyle>
                <Width>13</Width>
              </PenSerializable>
              <PlotStyle>Bar</PlotStyle>
            </Plot>
          </Plots>
          <PlotsConfigurable>true</PlotsConfigurable>
          <ScaleJustification>Right</ScaleJustification>
          <SelectedSeries>0</SelectedSeries>
          <SessionBreakLines>true</SessionBreakLines>
          <VerticalGridLines>true</VerticalGridLines>
          <ZOrder>30017</ZOrder>
          <SettingsSerializable>{"MultiplierForAverageDeviation":1.0,"AlertsEnableVisual":true,"AlertsEnableAudio":false}</SettingsSerializable>
          <PlotOpacity>7</PlotOpacity>
          <ShowPositiveZeroPointSeven>true</ShowPositiveZeroPointSeven>
          <ShowPositiveOne>true</ShowPositiveOne>
          <ShowPositiveOnePointFive>true</ShowPositiveOnePointFive>
          <ShowPositiveTwo>true</ShowPositiveTwo>
          <ShowPositiveThree>true</ShowPositiveThree>
        </SolidDeviation_03>
      </Indicator>
    </Indicator1>
    <Indicator2>
      <ClassName>NinjaTrader.Indicator.VolumeUpDown</ClassName>
      <Input>
        <PriceType>Close</PriceType>
      </Input>
      <BarsSeriesIdx>0</BarsSeriesIdx>
      <Indicator>
        <VolumeUpDown xmlns:xsi="http://www.w3.org/2001/XMLSchema-instance" xmlns:xsd="http://www.w3.org/2001/XMLSchema">
          <AllowRemovalOfDrawObjects>false</AllowRemovalOfDrawObjects>
          <AutoScale>true</AutoScale>
          <BarsPeriods>
            <Period>
              <BasePeriodType>Tick</BasePeriodType>
              <BasePeriodValue>100</BasePeriodValue>
              <Id>Custom8</Id>
              <MarketDataType>Last</MarketDataType>
              <PointAndFigurePriceType>Close</PointAndFigurePriceType>
              <ReversalType>Tick</ReversalType>
              <Value>10</Value>
              <Value2>50</Value2>
            </Period>
          </BarsPeriods>
          <CalculateOnBarClose>false</CalculateOnBarClose>
          <DisableScaleBuffer>false</DisableScaleBuffer>
          <Displacement>0</Displacement>
          <DisplayInDataBox>true</DisplayInDataBox>
          <DrawOnPricePanel>true</DrawOnPricePanel>
          <Enabled>true</Enabled>
          <ForceMaximumBarsLookBack256>false</ForceMaximumBarsLookBack256>
          <HorizontalGridLines>true</HorizontalGridLines>
          <InstrumentsSerializable>YM 06-16 Globex</InstrumentsSerializable>
          <Lines>
            <Line>
              <Name>Zero line</Name>
              <PenSerializable>
                <Color>n:DarkGray</Color>
                <DashStyle>Solid</DashStyle>
                <Width>1</Width>
              </PenSerializable>
              <Value>0</Value>
            </Line>
          </Lines>
          <LinesConfigurable>true</LinesConfigurable>
          <MaximumBarsLookBack>TwoHundredFiftySix</MaximumBarsLookBack>
          <Name />
          <Overlay>false</Overlay>
          <PaintPriceMarkers>true</PaintPriceMarkers>
          <Panel>3</Panel>
          <PanelUI>4</PanelUI>
          <Plots>
            <Plot>
              <Max>1.7976931348623157E+308</Max>
              <Min>-1.7976931348623157E+308</Min>
              <Name>UpVolume</Name>
              <PenSerializable>
                <Color>n:ForestGreen</Color>
                <DashStyle>Solid</DashStyle>
                <Width>3</Width>
              </PenSerializable>
              <PlotStyle>Bar</PlotStyle>
            </Plot>
            <Plot>
              <Max>1.7976931348623157E+308</Max>
              <Min>-1.7976931348623157E+308</Min>
              <Name>DownVolume</Name>
              <PenSerializable>
                <Color>n:Red</Color>
                <DashStyle>Solid</DashStyle>
                <Width>3</Width>
              </PenSerializable>
              <PlotStyle>Bar</PlotStyle>
            </Plot>
          </Plots>
          <PlotsConfigurable>true</PlotsConfigurable>
          <ScaleJustification>Right</ScaleJustification>
          <SelectedSeries>0</SelectedSeries>
          <SessionBreakLines>true</SessionBreakLines>
          <VerticalGridLines>true</VerticalGridLines>
          <ZOrder>30011</ZOrder>
        </VolumeUpDown>
      </Indicator>
    </Indicator2>
    <Indicator3>
      <ClassName>NinjaTrader.Indicator.ApexDiagnosticBarRange</ClassName>
      <Input>
        <PriceType>Close</PriceType>
      </Input>
      <BarsSeriesIdx>0</BarsSeriesIdx>
      <Indicator>
        <ApexDiagnosticBarRange xmlns:xsi="http://www.w3.org/2001/XMLSchema-instance" xmlns:xsd="http://www.w3.org/2001/XMLSchema">
          <AllowRemovalOfDrawObjects>false</AllowRemovalOfDrawObjects>
          <AutoScale>true</AutoScale>
          <BarsPeriods>
            <Period>
              <BasePeriodType>Tick</BasePeriodType>
              <BasePeriodValue>100</BasePeriodValue>
              <Id>Custom8</Id>
              <MarketDataType>Last</MarketDataType>
              <PointAndFigurePriceType>Close</PointAndFigurePriceType>
              <ReversalType>Tick</ReversalType>
              <Value>10</Value>
              <Value2>50</Value2>
            </Period>
          </BarsPeriods>
          <CalculateOnBarClose>false</CalculateOnBarClose>
          <DisableScaleBuffer>false</DisableScaleBuffer>
          <Displacement>0</Displacement>
          <DisplayInDataBox>false</DisplayInDataBox>
          <DrawOnPricePanel>true</DrawOnPricePanel>
          <Enabled>true</Enabled>
          <ForceMaximumBarsLookBack256>false</ForceMaximumBarsLookBack256>
          <HorizontalGridLines>true</HorizontalGridLines>
          <InstrumentsSerializable>YM 06-16 Globex</InstrumentsSerializable>
          <Lines />
          <LinesConfigurable>true</LinesConfigurable>
          <MaximumBarsLookBack>TwoHundredFiftySix</MaximumBarsLookBack>
          <Name>A.P.E.X. Diagnostic Bar Range</Name>
          <Overlay>true</Overlay>
          <PaintPriceMarkers>true</PaintPriceMarkers>
          <Panel>-2</Panel>
          <PanelUI>-1</PanelUI>
          <Plots>
            <Plot>
              <Max>1.7976931348623157E+308</Max>
              <Min>-1.7976931348623157E+308</Min>
              <Name>Dummy</Name>
              <PenSerializable>
                <Color>n:Orange</Color>
                <DashStyle>Solid</DashStyle>
                <Width>1</Width>
              </PenSerializable>
              <PlotStyle>Line</PlotStyle>
            </Plot>
          </Plots>
          <PlotsConfigurable>false</PlotsConfigurable>
          <ScaleJustification>Right</ScaleJustification>
          <SelectedSeries>0</SelectedSeries>
          <SessionBreakLines>true</SessionBreakLines>
          <VerticalGridLines>true</VerticalGridLines>
          <ZOrder>30019</ZOrder>
          <UpperLinePenSerializable>
            <Color>n:Black</Color>
            <DashStyle>Solid</DashStyle>
            <Width>2</Width>
          </UpperLinePenSerializable>
          <LowerLinePenSerializable>
            <Color>n:Black</Color>
            <DashStyle>Solid</DashStyle>
            <Width>2</Width>
          </LowerLinePenSerializable>
          <DrawText>true</DrawText>
          <DrawDiamondMarkers>true</DrawDiamondMarkers>
          <MarkerLineLength>10</MarkerLineLength>
          <RightShift>10</RightShift>
        </ApexDiagnosticBarRange>
      </Indicator>
    </Indicator3>
    <Indicator4>
      <ClassName>NinjaTrader.Indicator.ApexPowerlines</ClassName>
      <Input>
        <PriceType>Close</PriceType>
      </Input>
      <BarsSeriesIdx>0</BarsSeriesIdx>
      <Indicator>
        <ApexPowerlines xmlns:xsi="http://www.w3.org/2001/XMLSchema-instance" xmlns:xsd="http://www.w3.org/2001/XMLSchema">
          <AllowRemovalOfDrawObjects>false</AllowRemovalOfDrawObjects>
          <AutoScale>true</AutoScale>
          <BarsPeriods>
            <Period>
              <BasePeriodType>Tick</BasePeriodType>
              <BasePeriodValue>100</BasePeriodValue>
              <Id>Custom8</Id>
              <MarketDataType>Last</MarketDataType>
              <PointAndFigurePriceType>Close</PointAndFigurePriceType>
              <ReversalType>Tick</ReversalType>
              <Value>10</Value>
              <Value2>50</Value2>
            </Period>
          </BarsPeriods>
          <CalculateOnBarClose>false</CalculateOnBarClose>
          <DisableScaleBuffer>false</DisableScaleBuffer>
          <Displacement>0</Displacement>
          <DisplayInDataBox>false</DisplayInDataBox>
          <DrawOnPricePanel>true</DrawOnPricePanel>
          <Enabled>true</Enabled>
          <ForceMaximumBarsLookBack256>false</ForceMaximumBarsLookBack256>
          <HorizontalGridLines>true</HorizontalGridLines>
          <InstrumentsSerializable>YM 06-16 Globex</InstrumentsSerializable>
          <Lines />
          <LinesConfigurable>true</LinesConfigurable>
          <MaximumBarsLookBack>TwoHundredFiftySix</MaximumBarsLookBack>
          <Name>A.P.E.X. Diagnostic Elite Pattern</Name>
          <Overlay>true</Overlay>
          <PaintPriceMarkers>true</PaintPriceMarkers>
          <Panel>-2</Panel>
          <PanelUI>-1</PanelUI>
          <Plots>
            <Plot>
              <Max>1.7976931348623157E+308</Max>
              <Min>-1.7976931348623157E+308</Min>
              <Name>Dummy</Name>
              <PenSerializable>
                <Color>n:Orange</Color>
                <DashStyle>Solid</DashStyle>
                <Width>1</Width>
              </PenSerializable>
              <PlotStyle>Line</PlotStyle>
            </Plot>
          </Plots>
          <PlotsConfigurable>false</PlotsConfigurable>
          <ScaleJustification>Right</ScaleJustification>
          <SelectedSeries>0</SelectedSeries>
          <SessionBreakLines>true</SessionBreakLines>
          <VerticalGridLines>true</VerticalGridLines>
          <ZOrder>30011</ZOrder>
          <pl_directionChangeOffset>1</pl_directionChangeOffset>
          <plInitialPLDirection>Down</plInitialPLDirection>
          <EntryOffset>2</EntryOffset>
          <ViewReversalAPEX>false</ViewReversalAPEX>
          <APEXFontSerialize>
            <FontFamily>Arial</FontFamily>
            <Size>16.2</Size>
            <Style>Bold</Style>
          </APEXFontSerialize>
          <LongAPEXColorSerialize>n:Green</LongAPEXColorSerialize>
          <ShortAPEXColorSerialize>n:Red</ShortAPEXColorSerialize>
          <showOldE>true</showOldE>
          <oldEFontSerialize>
            <FontFamily>Arial</FontFamily>
            <Size>12</Size>
            <Style>Regular</Style>
          </oldEFontSerialize>
          <oldEColorSerialize>n:SaddleBrown</oldEColorSerialize>
        </ApexPowerlines>
      </Indicator>
    </Indicator4>
    <Indicator5>
      <ClassName>NinjaTrader.Indicator.ApexDiagnosticEMA</ClassName>
      <Input>
        <PriceType>Close</PriceType>
      </Input>
      <BarsSeriesIdx>0</BarsSeriesIdx>
      <Indicator>
        <ApexDiagnosticEMA xmlns:xsi="http://www.w3.org/2001/XMLSchema-instance" xmlns:xsd="http://www.w3.org/2001/XMLSchema">
          <AllowRemovalOfDrawObjects>false</AllowRemovalOfDrawObjects>
          <AutoScale>true</AutoScale>
          <BarsPeriods>
            <Period>
              <BasePeriodType>Tick</BasePeriodType>
              <BasePeriodValue>100</BasePeriodValue>
              <Id>Custom8</Id>
              <MarketDataType>Last</MarketDataType>
              <PointAndFigurePriceType>Close</PointAndFigurePriceType>
              <ReversalType>Tick</ReversalType>
              <Value>10</Value>
              <Value2>50</Value2>
            </Period>
          </BarsPeriods>
          <CalculateOnBarClose>true</CalculateOnBarClose>
          <DisableScaleBuffer>false</DisableScaleBuffer>
          <Displacement>0</Displacement>
          <DisplayInDataBox>true</DisplayInDataBox>
          <DrawOnPricePanel>true</DrawOnPricePanel>
          <Enabled>true</Enabled>
          <ForceMaximumBarsLookBack256>false</ForceMaximumBarsLookBack256>
          <HorizontalGridLines>true</HorizontalGridLines>
          <InstrumentsSerializable>YM 06-16 Globex</InstrumentsSerializable>
          <Lines />
          <LinesConfigurable>true</LinesConfigurable>
          <MaximumBarsLookBack>TwoHundredFiftySix</MaximumBarsLookBack>
          <Name>A.P.E.X. Diagnostic EMA</Name>
          <Overlay>true</Overlay>
          <PaintPriceMarkers>true</PaintPriceMarkers>
          <Panel>-2</Panel>
          <PanelUI>-1</PanelUI>
          <Plots>
            <Plot>
              <Max>1.7976931348623157E+308</Max>
              <Min>-1.7976931348623157E+308</Min>
              <Name>EMA</Name>
              <PenSerializable>
                <Color>n:DarkViolet</Color>
                <DashStyle>Solid</DashStyle>
                <Width>3</Width>
              </PenSerializable>
              <PlotStyle>Line</PlotStyle>
            </Plot>
          </Plots>
          <PlotsConfigurable>true</PlotsConfigurable>
          <ScaleJustification>Right</ScaleJustification>
          <SelectedSeries>0</SelectedSeries>
          <SessionBreakLines>true</SessionBreakLines>
          <VerticalGridLines>true</VerticalGridLines>
          <ZOrder>30015</ZOrder>
          <Period>50</Period>
        </ApexDiagnosticEMA>
      </Indicator>
    </Indicator5>
    <Indicator6>
      <ClassName>NinjaTrader.Indicator.ApexDiagnosticExpectedRange03</ClassName>
      <Input>
        <PriceType>Close</PriceType>
      </Input>
      <BarsSeriesIdx>0</BarsSeriesIdx>
      <Indicator>
        <ApexDiagnosticExpectedRange03 xmlns:xsi="http://www.w3.org/2001/XMLSchema-instance" xmlns:xsd="http://www.w3.org/2001/XMLSchema">
          <AllowRemovalOfDrawObjects>false</AllowRemovalOfDrawObjects>
          <AutoScale>true</AutoScale>
          <BarsPeriods>
            <Period>
              <BasePeriodType>Tick</BasePeriodType>
              <BasePeriodValue>100</BasePeriodValue>
              <Id>Custom8</Id>
              <MarketDataType>Last</MarketDataType>
              <PointAndFigurePriceType>Close</PointAndFigurePriceType>
              <ReversalType>Tick</ReversalType>
              <Value>10</Value>
              <Value2>50</Value2>
            </Period>
            <Period>
              <BasePeriodType>Minute</BasePeriodType>
              <BasePeriodValue>1</BasePeriodValue>
              <Id>Minute</Id>
              <MarketDataType>Last</MarketDataType>
              <PointAndFigurePriceType>Close</PointAndFigurePriceType>
              <ReversalType>Tick</ReversalType>
              <Value>1</Value>
              <Value2>1</Value2>
            </Period>
          </BarsPeriods>
          <CalculateOnBarClose>false</CalculateOnBarClose>
          <DisableScaleBuffer>false</DisableScaleBuffer>
          <Displacement>0</Displacement>
          <DisplayInDataBox>true</DisplayInDataBox>
          <DrawOnPricePanel>true</DrawOnPricePanel>
          <Enabled>true</Enabled>
          <ForceMaximumBarsLookBack256>false</ForceMaximumBarsLookBack256>
          <HorizontalGridLines>true</HorizontalGridLines>
          <InstrumentsSerializable>YM 06-16 Globex|YM 06-16 Globex</InstrumentsSerializable>
          <Lines />
          <LinesConfigurable>true</LinesConfigurable>
          <MaximumBarsLookBack>TwoHundredFiftySix</MaximumBarsLookBack>
          <Name />
          <Overlay>false</Overlay>
          <PaintPriceMarkers>true</PaintPriceMarkers>
          <Panel>1</Panel>
          <PanelUI>2</PanelUI>
          <Plots>
            <Plot>
              <Max>1.7976931348623157E+308</Max>
              <Min>-1.7976931348623157E+308</Min>
              <Name>Alarm</Name>
              <PenSerializable>
                <Color>n:Transparent</Color>
                <DashStyle>Dash</DashStyle>
                <Width>1</Width>
              </PenSerializable>
              <PlotStyle>Square</PlotStyle>
            </Plot>
            <Plot>
              <Max>1.7976931348623157E+308</Max>
              <Min>-1.7976931348623157E+308</Min>
              <Name>Expected</Name>
              <PenSerializable>
                <Color>n:Transparent</Color>
                <DashStyle>Solid</DashStyle>
                <Width>3</Width>
              </PenSerializable>
              <PlotStyle>Square</PlotStyle>
            </Plot>
            <Plot>
              <Max>1.7976931348623157E+308</Max>
              <Min>-1.7976931348623157E+308</Min>
              <Name>Actual</Name>
              <PenSerializable>
                <Color>n:Transparent</Color>
                <DashStyle>Solid</DashStyle>
                <Width>3</Width>
              </PenSerializable>
              <PlotStyle>Line</PlotStyle>
            </Plot>
            <Plot>
              <Max>1.7976931348623157E+308</Max>
              <Min>-1.7976931348623157E+308</Min>
              <Name>From Low</Name>
              <PenSerializable>
                <Color>n:Transparent</Color>
                <DashStyle>Solid</DashStyle>
                <Width>13</Width>
              </PenSerializable>
              <PlotStyle>Bar</PlotStyle>
            </Plot>
            <Plot>
              <Max>1.7976931348623157E+308</Max>
              <Min>-1.7976931348623157E+308</Min>
              <Name>From High</Name>
              <PenSerializable>
                <Color>n:Transparent</Color>
                <DashStyle>Solid</DashStyle>
                <Width>13</Width>
              </PenSerializable>
              <PlotStyle>Bar</PlotStyle>
            </Plot>
          </Plots>
          <PlotsConfigurable>true</PlotsConfigurable>
          <ScaleJustification>Right</ScaleJustification>
          <SelectedSeries>0</SelectedSeries>
          <SessionBreakLines>true</SessionBreakLines>
          <VerticalGridLines>true</VerticalGridLines>
          <ZOrder>-10</ZOrder>
          <AlarmSettings>
            <Enabled>false</Enabled>
            <VoiceEnabled>false</VoiceEnabled>
            <AlarmPercent>75</AlarmPercent>
            <AlarmResetPercent>50</AlarmResetPercent>
            <MinimumNumberOfTicksRequiredToResetAlarm>0</MinimumNumberOfTicksRequiredToResetAlarm>
            <MinimumRangeTicks>0</MinimumRangeTicks>
          </AlarmSettings>
          <SettingsSerializable>{"PeriodInMinutes":60,"OffsetInMinutes":0,"RangeType":0}</SettingsSerializable>
          <DrawChannels>true</DrawChannels>
          <UpBoxColorSerializable>-9868951</UpBoxColorSerializable>
          <DownBoxColorSerializable>-9868951</DownBoxColorSerializable>
        </ApexDiagnosticExpectedRange03>
      </Indicator>
    </Indicator6>
    <Indicator7>
      <ClassName>NinjaTrader.Indicator.SolidDeviationLevels_03</ClassName>
      <Input>
        <PriceType>Close</PriceType>
      </Input>
      <BarsSeriesIdx>0</BarsSeriesIdx>
      <Indicator>
        <SolidDeviationLevels_03 xmlns:xsi="http://www.w3.org/2001/XMLSchema-instance" xmlns:xsd="http://www.w3.org/2001/XMLSchema">
          <AllowRemovalOfDrawObjects>false</AllowRemovalOfDrawObjects>
          <AutoScale>true</AutoScale>
          <BarsPeriods>
            <Period>
              <BasePeriodType>Tick</BasePeriodType>
              <BasePeriodValue>100</BasePeriodValue>
              <Id>Custom8</Id>
              <MarketDataType>Last</MarketDataType>
              <PointAndFigurePriceType>Close</PointAndFigurePriceType>
              <ReversalType>Tick</ReversalType>
              <Value>10</Value>
              <Value2>50</Value2>
            </Period>
            <Period>
              <BasePeriodType>Minute</BasePeriodType>
              <BasePeriodValue>1</BasePeriodValue>
              <Id>Minute</Id>
              <MarketDataType>Last</MarketDataType>
              <PointAndFigurePriceType>Close</PointAndFigurePriceType>
              <ReversalType>Tick</ReversalType>
              <Value>1</Value>
              <Value2>1</Value2>
            </Period>
          </BarsPeriods>
          <CalculateOnBarClose>false</CalculateOnBarClose>
          <DisableScaleBuffer>false</DisableScaleBuffer>
          <Displacement>0</Displacement>
          <DisplayInDataBox>false</DisplayInDataBox>
          <DrawOnPricePanel>true</DrawOnPricePanel>
          <Enabled>true</Enabled>
          <ForceMaximumBarsLookBack256>false</ForceMaximumBarsLookBack256>
          <HorizontalGridLines>true</HorizontalGridLines>
          <InstrumentsSerializable>YM 06-16 Globex|YM 06-16 Globex</InstrumentsSerializable>
          <Lines />
          <LinesConfigurable>true</LinesConfigurable>
          <MaximumBarsLookBack>Infinite</MaximumBarsLookBack>
          <Name>A.P.E.X. Diagnostic Deviation Levels</Name>
          <Overlay>true</Overlay>
          <PaintPriceMarkers>false</PaintPriceMarkers>
          <Panel>-2</Panel>
          <PanelUI>-1</PanelUI>
          <Plots>
            <Plot>
              <Max>1.7976931348623157E+308</Max>
              <Min>-1.7976931348623157E+308</Min>
              <Name>Dummy</Name>
              <PenSerializable>
                <Color>n:Orange</Color>
                <DashStyle>Solid</DashStyle>
                <Width>1</Width>
              </PenSerializable>
              <PlotStyle>Line</PlotStyle>
            </Plot>
          </Plots>
          <PlotsConfigurable>false</PlotsConfigurable>
          <ScaleJustification>Right</ScaleJustification>
          <SelectedSeries>0</SelectedSeries>
          <SessionBreakLines>true</SessionBreakLines>
          <VerticalGridLines>true</VerticalGridLines>
          <ZOrder>30018</ZOrder>
          <SettingsSerializable>{"MultiplierForAverageDeviation":1.0,"AlertsEnableVisual":false,"AlertsEnableAudio":false}</SettingsSerializable>
          <ShowLabels>true</ShowLabels>
          <LabelAlignment>Left</LabelAlignment>
          <ShowZones>true</ShowZones>
          <ZoneSizeInDeviations>1</ZoneSizeInDeviations>
          <ShowNegativeThree>true</ShowNegativeThree>
          <ShowNegativeTwo>true</ShowNegativeTwo>
          <ShowNegativeOnePointFive>true</ShowNegativeOnePointFive>
          <ShowNegativeOne>true</ShowNegativeOne>
          <ShowNegativeZeroPointSeven>true</ShowNegativeZeroPointSeven>
          <ShowNegativeZeroPointFive>true</ShowNegativeZeroPointFive>
          <ShowZero>true</ShowZero>
          <ShowPositiveZeroPointFive>true</ShowPositiveZeroPointFive>
          <ShowPositiveZeroPointSeven>true</ShowPositiveZeroPointSeven>
          <ShowPositiveOne>true</ShowPositiveOne>
          <ShowPositiveOnePointFive>true</ShowPositiveOnePointFive>
          <ShowPositiveTwo>true</ShowPositiveTwo>
          <ShowPositiveThree>true</ShowPositiveThree>
          <DrawingToolsetsSerializable>{"0":{"Color":"Cyan","LineWidth":3,"DashStyle":0,"ZoneOpacity":3,"LineOpacity":10},"0.5":{"Color":"CadetBlue","LineWidth":2,"DashStyle":3,"ZoneOpacity":3,"LineOpacity":10},"0.7":{"Color":"CadetBlue","LineWidth":2,"DashStyle":1,"ZoneOpacity":3,"LineOpacity":10},"1":{"Color":"MediumPurple","LineWidth":2,"DashStyle":0,"ZoneOpacity":3,"LineOpacity":10},"1.5":{"Color":"CadetBlue","LineWidth":2,"DashStyle":3,"ZoneOpacity":3,"LineOpacity":10},"2":{"Color":"MediumPurple","LineWidth":2,"DashStyle":0,"ZoneOpacity":3,"LineOpacity":10},"3":{"Color":"MediumPurple","LineWidth":2,"DashStyle":0,"ZoneOpacity":3,"LineOpacity":10},"-0.5":{"Color":"LightSteelBlue","LineWidth":2,"DashStyle":3,"ZoneOpacity":3,"LineOpacity":10},"-0.7":{"Color":"CadetBlue","LineWidth":2,"DashStyle":1,"ZoneOpacity":3,"LineOpacity":10},"-1":{"Color":"MediumPurple","LineWidth":2,"DashStyle":0,"ZoneOpacity":3,"LineOpacity":10},"-1.5":{"Color":"LightSteelBlue","LineWidth":2,"DashStyle":3,"ZoneOpacity":3,"LineOpacity":10},"-2":{"Color":"MediumPurple","LineWidth":1,"DashStyle":0,"ZoneOpacity":3,"LineOpacity":10},"-3":{"Color":"MediumPurple","LineWidth":1,"DashStyle":0,"ZoneOpacity":3,"LineOpacity":10}}</DrawingToolsetsSerializable>
        </SolidDeviationLevels_03>
      </Indicator>
    </Indicator7>
    <Indicator8>
      <ClassName>NinjaTrader.Indicator.CurrentDayOHL</ClassName>
      <Input>
        <PriceType>Close</PriceType>
      </Input>
      <BarsSeriesIdx>0</BarsSeriesIdx>
      <Indicator>
        <CurrentDayOHL xmlns:xsi="http://www.w3.org/2001/XMLSchema-instance" xmlns:xsd="http://www.w3.org/2001/XMLSchema">
          <AllowRemovalOfDrawObjects>false</AllowRemovalOfDrawObjects>
          <AutoScale>false</AutoScale>
          <BarsPeriods>
            <Period>
              <BasePeriodType>Tick</BasePeriodType>
              <BasePeriodValue>100</BasePeriodValue>
              <Id>Custom8</Id>
              <MarketDataType>Last</MarketDataType>
              <PointAndFigurePriceType>Close</PointAndFigurePriceType>
              <ReversalType>Tick</ReversalType>
              <Value>10</Value>
              <Value2>50</Value2>
            </Period>
          </BarsPeriods>
          <CalculateOnBarClose>true</CalculateOnBarClose>
          <DisableScaleBuffer>false</DisableScaleBuffer>
          <Displacement>0</Displacement>
          <DisplayInDataBox>true</DisplayInDataBox>
          <DrawOnPricePanel>true</DrawOnPricePanel>
          <Enabled>true</Enabled>
          <ForceMaximumBarsLookBack256>false</ForceMaximumBarsLookBack256>
          <HorizontalGridLines>true</HorizontalGridLines>
          <InstrumentsSerializable>YM 06-16 Globex</InstrumentsSerializable>
          <Lines />
          <LinesConfigurable>true</LinesConfigurable>
          <MaximumBarsLookBack>TwoHundredFiftySix</MaximumBarsLookBack>
          <Name>CurrentDayOHL</Name>
          <Overlay>true</Overlay>
          <PaintPriceMarkers>true</PaintPriceMarkers>
          <Panel>-2</Panel>
          <PanelUI>-1</PanelUI>
          <Plots>
            <Plot>
              <Max>1.7976931348623157E+308</Max>
              <Min>-1.7976931348623157E+308</Min>
              <Name>Current Open</Name>
              <PenSerializable>
                <Color>n:Cyan</Color>
                <DashStyle>Dot</DashStyle>
                <Width>2</Width>
              </PenSerializable>
              <PlotStyle>Square</PlotStyle>
            </Plot>
            <Plot>
              <Max>1.7976931348623157E+308</Max>
              <Min>-1.7976931348623157E+308</Min>
              <Name>Current High</Name>
              <PenSerializable>
                <Color>n:Green</Color>
                <DashStyle>Dash</DashStyle>
                <Width>3</Width>
              </PenSerializable>
              <PlotStyle>Line</PlotStyle>
            </Plot>
            <Plot>
              <Max>1.7976931348623157E+308</Max>
              <Min>-1.7976931348623157E+308</Min>
              <Name>Current Low</Name>
              <PenSerializable>
                <Color>n:OrangeRed</Color>
                <DashStyle>Dash</DashStyle>
                <Width>3</Width>
              </PenSerializable>
              <PlotStyle>Line</PlotStyle>
            </Plot>
          </Plots>
          <PlotsConfigurable>true</PlotsConfigurable>
          <ScaleJustification>Right</ScaleJustification>
          <SelectedSeries>0</SelectedSeries>
          <SessionBreakLines>true</SessionBreakLines>
          <VerticalGridLines>true</VerticalGridLines>
          <ZOrder>30016</ZOrder>
          <ShowOpen>true</ShowOpen>
          <ShowHigh>true</ShowHigh>
          <PlotCurrentValue>false</PlotCurrentValue>
          <ShowLow>true</ShowLow>
        </CurrentDayOHL>
      </Indicator>
    </Indicator8>
    <Indicator9>
      <ClassName>NinjaTrader.Indicator.PriorDayOHLC</ClassName>
      <Input>
        <PriceType>Close</PriceType>
      </Input>
      <BarsSeriesIdx>0</BarsSeriesIdx>
      <Indicator>
        <PriorDayOHLC xmlns:xsi="http://www.w3.org/2001/XMLSchema-instance" xmlns:xsd="http://www.w3.org/2001/XMLSchema">
          <AllowRemovalOfDrawObjects>false</AllowRemovalOfDrawObjects>
          <AutoScale>false</AutoScale>
          <BarsPeriods>
            <Period>
              <BasePeriodType>Tick</BasePeriodType>
              <BasePeriodValue>100</BasePeriodValue>
              <Id>Custom8</Id>
              <MarketDataType>Last</MarketDataType>
              <PointAndFigurePriceType>Close</PointAndFigurePriceType>
              <ReversalType>Tick</ReversalType>
              <Value>10</Value>
              <Value2>50</Value2>
            </Period>
          </BarsPeriods>
          <CalculateOnBarClose>true</CalculateOnBarClose>
          <DisableScaleBuffer>false</DisableScaleBuffer>
          <Displacement>0</Displacement>
          <DisplayInDataBox>true</DisplayInDataBox>
          <DrawOnPricePanel>true</DrawOnPricePanel>
          <Enabled>true</Enabled>
          <ForceMaximumBarsLookBack256>false</ForceMaximumBarsLookBack256>
          <HorizontalGridLines>true</HorizontalGridLines>
          <InstrumentsSerializable>YM 06-16 Globex</InstrumentsSerializable>
          <Lines />
          <LinesConfigurable>true</LinesConfigurable>
          <MaximumBarsLookBack>TwoHundredFiftySix</MaximumBarsLookBack>
          <Name>PriorDayOHLC</Name>
          <Overlay>true</Overlay>
          <PaintPriceMarkers>true</PaintPriceMarkers>
          <Panel>-2</Panel>
          <PanelUI>-1</PanelUI>
          <Plots>
            <Plot>
              <Max>1.7976931348623157E+308</Max>
              <Min>-1.7976931348623157E+308</Min>
              <Name>Prior Open</Name>
              <PenSerializable>
                <Color>n:Transparent</Color>
                <DashStyle>Dash</DashStyle>
                <Width>1</Width>
              </PenSerializable>
              <PlotStyle>Hash</PlotStyle>
            </Plot>
            <Plot>
              <Max>1.7976931348623157E+308</Max>
              <Min>-1.7976931348623157E+308</Min>
              <Name>Prior High</Name>
              <PenSerializable>
                <Color>n:DarkOliveGreen</Color>
                <DashStyle>Dot</DashStyle>
                <Width>3</Width>
              </PenSerializable>
              <PlotStyle>Line</PlotStyle>
            </Plot>
            <Plot>
              <Max>1.7976931348623157E+308</Max>
              <Min>-1.7976931348623157E+308</Min>
              <Name>Prior Low</Name>
              <PenSerializable>
                <Color>n:Firebrick</Color>
                <DashStyle>Dot</DashStyle>
                <Width>3</Width>
              </PenSerializable>
              <PlotStyle>Line</PlotStyle>
            </Plot>
            <Plot>
              <Max>1.7976931348623157E+308</Max>
              <Min>-1.7976931348623157E+308</Min>
              <Name>Prior Close</Name>
              <PenSerializable>
                <Color>n:Transparent</Color>
                <DashStyle>Solid</DashStyle>
                <Width>2</Width>
              </PenSerializable>
              <PlotStyle>Dot</PlotStyle>
            </Plot>
          </Plots>
          <PlotsConfigurable>true</PlotsConfigurable>
          <ScaleJustification>Right</ScaleJustification>
          <SelectedSeries>0</SelectedSeries>
          <SessionBreakLines>true</SessionBreakLines>
          <VerticalGridLines>true</VerticalGridLines>
          <ZOrder>30012</ZOrder>
          <ShowOpen>true</ShowOpen>
          <ShowHigh>true</ShowHigh>
          <ShowLow>true</ShowLow>
          <ShowClose>true</ShowClose>
        </PriorDayOHLC>
      </Indicator>
    </Indicator9>
    <Indicator10>
      <ClassName>NinjaTrader.Indicator.ApexDiagnosticMVP</ClassName>
      <Input>
        <PriceType>Close</PriceType>
      </Input>
      <BarsSeriesIdx>0</BarsSeriesIdx>
      <Indicator>
        <ApexDiagnosticMVP xmlns:xsi="http://www.w3.org/2001/XMLSchema-instance" xmlns:xsd="http://www.w3.org/2001/XMLSchema">
          <AllowRemovalOfDrawObjects>false</AllowRemovalOfDrawObjects>
          <AutoScale>true</AutoScale>
          <BarsPeriods>
            <Period>
              <BasePeriodType>Tick</BasePeriodType>
              <BasePeriodValue>100</BasePeriodValue>
              <Id>Custom8</Id>
              <MarketDataType>Last</MarketDataType>
              <PointAndFigurePriceType>Close</PointAndFigurePriceType>
              <ReversalType>Tick</ReversalType>
              <Value>10</Value>
              <Value2>50</Value2>
            </Period>
          </BarsPeriods>
          <CalculateOnBarClose>true</CalculateOnBarClose>
          <DisableScaleBuffer>false</DisableScaleBuffer>
          <Displacement>0</Displacement>
          <DisplayInDataBox>true</DisplayInDataBox>
          <DrawOnPricePanel>true</DrawOnPricePanel>
          <Enabled>true</Enabled>
          <ForceMaximumBarsLookBack256>false</ForceMaximumBarsLookBack256>
          <HorizontalGridLines>true</HorizontalGridLines>
          <InstrumentsSerializable>YM 06-16 Globex</InstrumentsSerializable>
          <Lines />
          <LinesConfigurable>true</LinesConfigurable>
          <MaximumBarsLookBack>Infinite</MaximumBarsLookBack>
          <Name>A.P.E.X. Diagnostic MVP</Name>
          <Overlay>true</Overlay>
          <PaintPriceMarkers>true</PaintPriceMarkers>
          <Panel>-2</Panel>
          <PanelUI>-1</PanelUI>
          <Plots>
            <Plot>
              <Max>1.7976931348623157E+308</Max>
              <Min>-1.7976931348623157E+308</Min>
              <Name>Momentum Predictor Line Up</Name>
              <PenSerializable>
                <Color>n:RoyalBlue</Color>
                <DashStyle>Solid</DashStyle>
                <Width>2</Width>
              </PenSerializable>
              <PlotStyle>TriangleUp</PlotStyle>
            </Plot>
            <Plot>
              <Max>1.7976931348623157E+308</Max>
              <Min>-1.7976931348623157E+308</Min>
              <Name>Momentum Predictor Line Down</Name>
              <PenSerializable>
                <Color>n:RoyalBlue</Color>
                <DashStyle>Solid</DashStyle>
                <Width>2</Width>
              </PenSerializable>
              <PlotStyle>TriangleDown</PlotStyle>
            </Plot>
            <Plot>
              <Max>1.7976931348623157E+308</Max>
              <Min>-1.7976931348623157E+308</Min>
              <Name>Volatile Trend Line - Short</Name>
              <PenSerializable>
                <Color>n:Transparent</Color>
                <DashStyle>Solid</DashStyle>
                <Width>3</Width>
              </PenSerializable>
              <PlotStyle>Line</PlotStyle>
            </Plot>
            <Plot>
              <Max>1.7976931348623157E+308</Max>
              <Min>-1.7976931348623157E+308</Min>
              <Name>Volatile Trend Line - Long</Name>
              <PenSerializable>
                <Color>n:Transparent</Color>
                <DashStyle>Solid</DashStyle>
                <Width>3</Width>
              </PenSerializable>
              <PlotStyle>Line</PlotStyle>
            </Plot>
            <Plot>
              <Max>1.7976931348623157E+308</Max>
              <Min>-1.7976931348623157E+308</Min>
              <Name>Offset Volatile Trend Line - Short</Name>
              <PenSerializable>
                <Color>n:Transparent</Color>
                <DashStyle>Dash</DashStyle>
                <Width>3</Width>
              </PenSerializable>
              <PlotStyle>Line</PlotStyle>
            </Plot>
            <Plot>
              <Max>1.7976931348623157E+308</Max>
              <Min>-1.7976931348623157E+308</Min>
              <Name>Offset Volatile Trend Line - Long</Name>
              <PenSerializable>
                <Color>n:Transparent</Color>
                <DashStyle>Dash</DashStyle>
                <Width>3</Width>
              </PenSerializable>
              <PlotStyle>Line</PlotStyle>
            </Plot>
            <Plot>
              <Max>1.7976931348623157E+308</Max>
              <Min>-1.7976931348623157E+308</Min>
              <Name>Trigger Price</Name>
              <PenSerializable>
                <Color>n:Transparent</Color>
                <DashStyle>Dash</DashStyle>
                <Width>1</Width>
              </PenSerializable>
              <PlotStyle>Line</PlotStyle>
            </Plot>
          </Plots>
          <PlotsConfigurable>true</PlotsConfigurable>
          <ScaleJustification>Right</ScaleJustification>
          <SelectedSeries>0</SelectedSeries>
          <SessionBreakLines>true</SessionBreakLines>
          <VerticalGridLines>true</VerticalGridLines>
          <ZOrder>30018</ZOrder>
          <SettingsSerializable>{"VolatileTrendLine":{"Period":5,"Multiplier":1.5,"OffsetTicks":10,"FlipStyle":1},"VolatileTrendLineFlip":{"RequirePredictorLine":true,"RequireMomentumPredictorLine":true},"MomentumPredictorFlip":{"MomentumLinePeriod":22,"NumConsecutiveBars":2,"Lookback":6},"Signals":{"Mode":0,"BreakoutTicks":2,"EnableSequential":true}}</SettingsSerializable>
          <Signals_Mode>InstantSignal</Signals_Mode>
          <Signals_BreakoutTicks>2</Signals_BreakoutTicks>
          <Signals_EnableSequential>true</Signals_EnableSequential>
          <EnableAlerts>true</EnableAlerts>
          <EnableVoiceAlerts>false</EnableVoiceAlerts>
          <ShowSignalArrows>true</ShowSignalArrows>
          <ShowSignalArrowLabels>false</ShowSignalArrowLabels>
          <ShowTriggerPriceLine>false</ShowTriggerPriceLine>
          <ShowTriggerPriceLabel>false</ShowTriggerPriceLabel>
          <SignalColorUpSerializable>-16744448</SignalColorUpSerializable>
          <SignalColorDownSerializable>-65536</SignalColorDownSerializable>
          <LabelFontSerializable />
        </ApexDiagnosticMVP>
      </Indicator>
    </Indicator10>
    <Indicator11>
      <ClassName>NinjaTrader.Indicator.ExpectedVolume07</ClassName>
      <Input>
        <PriceType>Close</PriceType>
      </Input>
      <BarsSeriesIdx>0</BarsSeriesIdx>
      <Indicator>
        <ExpectedVolume07 xmlns:xsi="http://www.w3.org/2001/XMLSchema-instance" xmlns:xsd="http://www.w3.org/2001/XMLSchema">
          <AllowRemovalOfDrawObjects>false</AllowRemovalOfDrawObjects>
          <AutoScale>true</AutoScale>
          <BarsPeriods>
            <Period>
              <BasePeriodType>Tick</BasePeriodType>
              <BasePeriodValue>100</BasePeriodValue>
              <Id>Custom8</Id>
              <MarketDataType>Last</MarketDataType>
              <PointAndFigurePriceType>Close</PointAndFigurePriceType>
              <ReversalType>Tick</ReversalType>
              <Value>10</Value>
              <Value2>50</Value2>
            </Period>
          </BarsPeriods>
          <CalculateOnBarClose>false</CalculateOnBarClose>
          <DisableScaleBuffer>false</DisableScaleBuffer>
          <Displacement>0</Displacement>
          <DisplayInDataBox>true</DisplayInDataBox>
          <DrawOnPricePanel>true</DrawOnPricePanel>
          <Enabled>true</Enabled>
          <ForceMaximumBarsLookBack256>false</ForceMaximumBarsLookBack256>
          <HorizontalGridLines>true</HorizontalGridLines>
          <InstrumentsSerializable>YM 06-16 Globex</InstrumentsSerializable>
          <Lines />
          <LinesConfigurable>true</LinesConfigurable>
          <MaximumBarsLookBack>TwoHundredFiftySix</MaximumBarsLookBack>
          <Name>A.P.E.X. Diagnostic Expected Volume v7</Name>
          <Overlay>false</Overlay>
          <PaintPriceMarkers>true</PaintPriceMarkers>
          <Panel>2</Panel>
          <PanelUI>3</PanelUI>
          <Plots>
            <Plot>
              <Max>1.7976931348623157E+308</Max>
              <Min>-1.7976931348623157E+308</Min>
              <Name>Alarm Threshold</Name>
              <PenSerializable>
                <Color>n:Black</Color>
                <DashStyle>Dash</DashStyle>
                <Width>1</Width>
              </PenSerializable>
              <PlotStyle>Square</PlotStyle>
            </Plot>
            <Plot>
              <Max>1.7976931348623157E+308</Max>
              <Min>-1.7976931348623157E+308</Min>
              <Name>Expected Volume</Name>
              <PenSerializable>
                <Color>n:Gold</Color>
                <DashStyle>Solid</DashStyle>
                <Width>3</Width>
              </PenSerializable>
              <PlotStyle>Square</PlotStyle>
            </Plot>
            <Plot>
              <Max>1.7976931348623157E+308</Max>
              <Min>-1.7976931348623157E+308</Min>
              <Name>Actual Volume</Name>
              <PenSerializable>
                <Color>n:MediumSlateBlue</Color>
                <DashStyle>Solid</DashStyle>
                <Width>13</Width>
              </PenSerializable>
              <PlotStyle>Bar</PlotStyle>
            </Plot>
          </Plots>
          <PlotsConfigurable>true</PlotsConfigurable>
          <ScaleJustification>Right</ScaleJustification>
          <SelectedSeries>0</SelectedSeries>
          <SessionBreakLines>true</SessionBreakLines>
          <VerticalGridLines>true</VerticalGridLines>
          <ZOrder>10003</ZOrder>
          <SettingsSerialized>{"useFuturesVolumeForForex":true,"minuteBarSettings":{"periodLengthStyle":"AutoDetect","periodEndStyle":"Offset","periodLengthInMinutes":10,"periodOffsetInMinutes":0},"diagnosticBarSettings":{"periodEndStyle":"UseEndMinuteOfCurrentBar","periodLengthInMinutes":10,"periodOffsetInMinutes":0,"alertStyle":"PotentialAndConfirmed"},"dropSpikes":true,"dropZeros":false,"spikeFactor":2.0,"alertThreshold":1.0}</SettingsSerialized>
          <UserSettingsSerialized>{"expectedVolumePen":{"color":"Yellow","dashStyle":0,"width":3.0},"alarmThresholdPen":{"color":"Black","dashStyle":1,"width":1.0},"actualVolumeColor":"LightSteelBlue","alertsVisualEnabled":false,"alertsAudibleEnabled":false,"alertsWindowFlashEnabled":false,"showVolumeLabels":true}</UserSettingsSerialized>
        </ExpectedVolume07>
      </Indicator>
    </Indicator11>
  </Indicators>
  <Panels>
    <Panel0>
      <HeightRatio>0.724035608308605</HeightRatio>
      <Index>0</Index>
      <Maximized>False</Maximized>
      <AutoScaleDateRangeTypeRight>ScreenDateRange</AutoScaleDateRangeTypeRight>
      <AutoScaleMarginLowerRight>3</AutoScaleMarginLowerRight>
      <AutoScaleMarginTypeRight>Percent</AutoScaleMarginTypeRight>
      <AutoScaleMarginUpperRight>3</AutoScaleMarginUpperRight>
      <YAxisRangeTypeRight>Automatic</YAxisRangeTypeRight>
      <FixedPanelMaxRight>17144.6070367865</FixedPanelMaxRight>
      <FixedPanelMinRight>16937.6128363636</FixedPanelMinRight>
      <YAxisScalingTypeRight>Linear</YAxisScalingTypeRight>
      <HorizontalGridLinesIntervalRight>0</HorizontalGridLinesIntervalRight>
      <HorizontalGridLinesIntervalTypeRight>Points</HorizontalGridLinesIntervalTypeRight>
      <AutoScaleDateRangeTypeLeft>ScreenDateRange</AutoScaleDateRangeTypeLeft>
      <AutoScaleMarginLowerLeft>3</AutoScaleMarginLowerLeft>
      <AutoScaleMarginTypeLeft>Percent</AutoScaleMarginTypeLeft>
      <AutoScaleMarginUpperLeft>3</AutoScaleMarginUpperLeft>
      <YAxisRangeTypeLeft>Automatic</YAxisRangeTypeLeft>
      <FixedPanelMaxLeft>1.03</FixedPanelMaxLeft>
      <FixedPanelMinLeft>-0.03</FixedPanelMinLeft>
      <YAxisScalingTypeLeft>Linear</YAxisScalingTypeLeft>
      <HorizontalGridLinesIntervalLeft>0</HorizontalGridLinesIntervalLeft>
      <HorizontalGridLinesIntervalTypeLeft>Points</HorizontalGridLinesIntervalTypeLeft>
      <AutoScaleDateRangeTypeOver>ScreenDateRange</AutoScaleDateRangeTypeOver>
      <AutoScaleMarginLowerOver>3</AutoScaleMarginLowerOver>
      <AutoScaleMarginTypeOver>Percent</AutoScaleMarginTypeOver>
      <AutoScaleMarginUpperOver>3</AutoScaleMarginUpperOver>
      <YAxisRangeTypeOver>Automatic</YAxisRangeTypeOver>
      <FixedPanelMaxOver>1.03</FixedPanelMaxOver>
      <FixedPanelMinOver>-0.03</FixedPanelMinOver>
      <YAxisScalingTypeOver>Linear</YAxisScalingTypeOver>
    </Panel0>
    <Panel1>
      <HeightRatio>0.105341246290801</HeightRatio>
      <Index>1</Index>
      <Maximized>False</Maximized>
      <AutoScaleDateRangeTypeRight>ScreenDateRange</AutoScaleDateRangeTypeRight>
      <AutoScaleMarginLowerRight>3</AutoScaleMarginLowerRight>
      <AutoScaleMarginTypeRight>Percent</AutoScaleMarginTypeRight>
      <AutoScaleMarginUpperRight>3</AutoScaleMarginUpperRight>
      <YAxisRangeTypeRight>Automatic</YAxisRangeTypeRight>
      <FixedPanelMaxRight>18126.00634</FixedPanelMaxRight>
      <FixedPanelMinRight>-1055.30634</FixedPanelMinRight>
      <YAxisScalingTypeRight>Linear</YAxisScalingTypeRight>
      <HorizontalGridLinesIntervalRight>0</HorizontalGridLinesIntervalRight>
      <HorizontalGridLinesIntervalTypeRight>Points</HorizontalGridLinesIntervalTypeRight>
      <AutoScaleDateRangeTypeLeft>ScreenDateRange</AutoScaleDateRangeTypeLeft>
      <AutoScaleMarginLowerLeft>3</AutoScaleMarginLowerLeft>
      <AutoScaleMarginTypeLeft>Percent</AutoScaleMarginTypeLeft>
      <AutoScaleMarginUpperLeft>3</AutoScaleMarginUpperLeft>
      <YAxisRangeTypeLeft>Automatic</YAxisRangeTypeLeft>
      <FixedPanelMaxLeft>1.03</FixedPanelMaxLeft>
      <FixedPanelMinLeft>-0.03</FixedPanelMinLeft>
      <YAxisScalingTypeLeft>Linear</YAxisScalingTypeLeft>
      <HorizontalGridLinesIntervalLeft>0</HorizontalGridLinesIntervalLeft>
      <HorizontalGridLinesIntervalTypeLeft>Points</HorizontalGridLinesIntervalTypeLeft>
      <AutoScaleDateRangeTypeOver>ScreenDateRange</AutoScaleDateRangeTypeOver>
      <AutoScaleMarginLowerOver>3</AutoScaleMarginLowerOver>
      <AutoScaleMarginTypeOver>Percent</AutoScaleMarginTypeOver>
      <AutoScaleMarginUpperOver>3</AutoScaleMarginUpperOver>
      <YAxisRangeTypeOver>Automatic</YAxisRangeTypeOver>
      <FixedPanelMaxOver>1.03</FixedPanelMaxOver>
      <FixedPanelMinOver>-0.03</FixedPanelMinOver>
      <YAxisScalingTypeOver>Linear</YAxisScalingTypeOver>
    </Panel1>
    <Panel2>
      <HeightRatio>0.0714285714285714</HeightRatio>
      <Index>2</Index>
      <Maximized>False</Maximized>
      <AutoScaleDateRangeTypeRight>ScreenDateRange</AutoScaleDateRangeTypeRight>
      <AutoScaleMarginLowerRight>3</AutoScaleMarginLowerRight>
      <AutoScaleMarginTypeRight>Percent</AutoScaleMarginTypeRight>
      <AutoScaleMarginUpperRight>3</AutoScaleMarginUpperRight>
      <YAxisRangeTypeRight>Automatic</YAxisRangeTypeRight>
      <FixedPanelMaxRight>2987.9052</FixedPanelMaxRight>
      <FixedPanelMinRight>-173.9052</FixedPanelMinRight>
      <YAxisScalingTypeRight>Linear</YAxisScalingTypeRight>
      <HorizontalGridLinesIntervalRight>0</HorizontalGridLinesIntervalRight>
      <HorizontalGridLinesIntervalTypeRight>Points</HorizontalGridLinesIntervalTypeRight>
      <AutoScaleDateRangeTypeLeft>ScreenDateRange</AutoScaleDateRangeTypeLeft>
      <AutoScaleMarginLowerLeft>3</AutoScaleMarginLowerLeft>
      <AutoScaleMarginTypeLeft>Percent</AutoScaleMarginTypeLeft>
      <AutoScaleMarginUpperLeft>3</AutoScaleMarginUpperLeft>
      <YAxisRangeTypeLeft>Automatic</YAxisRangeTypeLeft>
      <FixedPanelMaxLeft>1.03</FixedPanelMaxLeft>
      <FixedPanelMinLeft>-0.03</FixedPanelMinLeft>
      <YAxisScalingTypeLeft>Linear</YAxisScalingTypeLeft>
      <HorizontalGridLinesIntervalLeft>0</HorizontalGridLinesIntervalLeft>
      <HorizontalGridLinesIntervalTypeLeft>Points</HorizontalGridLinesIntervalTypeLeft>
      <AutoScaleDateRangeTypeOver>ScreenDateRange</AutoScaleDateRangeTypeOver>
      <AutoScaleMarginLowerOver>3</AutoScaleMarginLowerOver>
      <AutoScaleMarginTypeOver>Percent</AutoScaleMarginTypeOver>
      <AutoScaleMarginUpperOver>3</AutoScaleMarginUpperOver>
      <YAxisRangeTypeOver>Automatic</YAxisRangeTypeOver>
      <FixedPanelMaxOver>1.03</FixedPanelMaxOver>
      <FixedPanelMinOver>-0.03</FixedPanelMinOver>
      <YAxisScalingTypeOver>Linear</YAxisScalingTypeOver>
    </Panel2>
    <Panel3>
      <HeightRatio>0.130841121495327</HeightRatio>
      <Index>3</Index>
      <Maximized>False</Maximized>
      <AutoScaleDateRangeTypeRight>ScreenDateRange</AutoScaleDateRangeTypeRight>
      <AutoScaleMarginLowerRight>3</AutoScaleMarginLowerRight>
      <AutoScaleMarginTypeRight>Percent</AutoScaleMarginTypeRight>
      <AutoScaleMarginUpperRight>3</AutoScaleMarginUpperRight>
      <YAxisRangeTypeRight>Automatic</YAxisRangeTypeRight>
      <FixedPanelMaxRight>1702.0654</FixedPanelMaxRight>
      <FixedPanelMinRight>-99.0654</FixedPanelMinRight>
      <YAxisScalingTypeRight>Linear</YAxisScalingTypeRight>
      <HorizontalGridLinesIntervalRight>0</HorizontalGridLinesIntervalRight>
      <HorizontalGridLinesIntervalTypeRight>Points</HorizontalGridLinesIntervalTypeRight>
      <AutoScaleDateRangeTypeLeft>ScreenDateRange</AutoScaleDateRangeTypeLeft>
      <AutoScaleMarginLowerLeft>3</AutoScaleMarginLowerLeft>
      <AutoScaleMarginTypeLeft>Percent</AutoScaleMarginTypeLeft>
      <AutoScaleMarginUpperLeft>3</AutoScaleMarginUpperLeft>
      <YAxisRangeTypeLeft>Automatic</YAxisRangeTypeLeft>
      <FixedPanelMaxLeft>1.03</FixedPanelMaxLeft>
      <FixedPanelMinLeft>-0.03</FixedPanelMinLeft>
      <YAxisScalingTypeLeft>Linear</YAxisScalingTypeLeft>
      <HorizontalGridLinesIntervalLeft>0</HorizontalGridLinesIntervalLeft>
      <HorizontalGridLinesIntervalTypeLeft>Points</HorizontalGridLinesIntervalTypeLeft>
      <AutoScaleDateRangeTypeOver>ScreenDateRange</AutoScaleDateRangeTypeOver>
      <AutoScaleMarginLowerOver>3</AutoScaleMarginLowerOver>
      <AutoScaleMarginTypeOver>Percent</AutoScaleMarginTypeOver>
      <AutoScaleMarginUpperOver>3</AutoScaleMarginUpperOver>
      <YAxisRangeTypeOver>Automatic</YAxisRangeTypeOver>
      <FixedPanelMaxOver>1.03</FixedPanelMaxOver>
      <FixedPanelMinOver>-0.03</FixedPanelMinOver>
      <YAxisScalingTypeOver>Linear</YAxisScalingTypeOver>
    </Panel3>
  </Panels>
  <Bars>
    <Bars0>
      <Bars>
        <BarsData xmlns:xsi="http://www.w3.org/2001/XMLSchema-instance" xmlns:xsd="http://www.w3.org/2001/XMLSchema">
          <AutoScale>true</AutoScale>
          <ChartStyleSerialize>&lt;ChartStyle&gt;&lt;BarWidth&gt;6.32620887909584&lt;/BarWidth&gt;&lt;ChartStyleType&gt;Custom1&lt;/ChartStyleType&gt;&lt;DownColor&gt;n:Black&lt;/DownColor&gt;&lt;Pen&gt;&amp;lt;Pen&amp;gt;&amp;lt;Color&amp;gt;n:Black&amp;lt;/Color&amp;gt;&amp;lt;DashStyle&amp;gt;Solid&amp;lt;/DashStyle&amp;gt;&amp;lt;Width&amp;gt;1&amp;lt;/Width&amp;gt;&amp;lt;/Pen&amp;gt;&lt;/Pen&gt;&lt;Pen2&gt;&amp;lt;Pen&amp;gt;&amp;lt;Color&amp;gt;n:Black&amp;lt;/Color&amp;gt;&amp;lt;DashStyle&amp;gt;Solid&amp;lt;/DashStyle&amp;gt;&amp;lt;Width&amp;gt;1&amp;lt;/Width&amp;gt;&amp;lt;/Pen&amp;gt;&lt;/Pen2&gt;&lt;UpColor&gt;n:Black&lt;/UpColor&gt;&lt;/ChartStyle&gt;</ChartStyleSerialize>
          <DisplayInDataBox>true</DisplayInDataBox>
          <LongExecutionColorSerialize>n:Blue</LongExecutionColorSerialize>
          <PaintPriceMarker>true</PaintPriceMarker>
          <Panel>0</Panel>
          <PanelUI>1</PanelUI>
          <PlotExecutions>DoNotPlot</PlotExecutions>
          <PlotSessionBreaks>true</PlotSessionBreaks>
          <PositionPenLooserSerializable>
            <Color>n:Crimson</Color>
            <DashStyle>Dot</DashStyle>
            <Width>2</Width>
          </PositionPenLooserSerializable>
          <PositionPenWinnerSerializable>
            <Color>n:DarkGreen</Color>
            <DashStyle>Dot</DashStyle>
            <Width>2</Width>
          </PositionPenWinnerSerializable>
          <PriceMarkerColorSerialize>n:Black</PriceMarkerColorSerialize>
          <ScaleJustification>Right</ScaleJustification>
          <SessionBreakPenSerializable>
            <Color>n:Silver</Color>
            <DashStyle>Solid</DashStyle>
            <Width>1</Width>
          </SessionBreakPenSerializable>
          <SessionData>&lt;Use instrument settings&gt;</SessionData>
          <ShortExecutionColorSerialize>n:Magenta</ShortExecutionColorSerialize>
          <ShowGlobalDrawObjects>true</ShowGlobalDrawObjects>
        </BarsData>
      </Bars>
    </Bars0>
  </Bars>
</NinjaTrader>